LICENSE
LICENSE.txt
README.rst
setup.py
src/__init__.py
src/underscore.py
underscore3/__init__.py
underscore3/underscore3.py
underscore3.egg-info/PKG-INFO
underscore3.egg-info/SOURCES.txt
underscore3.egg-info/dependency_links.txt
underscore3.egg-info/requires.txt
underscore3.egg-info/top_level.txt