Metadata-Version: 2.1
Name: underscore3
Version: 0.0.14
Summary: TBA
Home-page: https://github.com/sfinktah/underscore3
Author: Christopher Anderson
Author-email: sfinktah@github.spamtrak.org
License: MIT
Platform: UNKNOWN
Classifier: Programming Language :: Python :: 3
Classifier: License :: OSI Approved :: MIT License
Classifier: Operating System :: OS Independent
Requires-Python: >=3.7
License-File: LICENSE
License-File: LICENSE.txt
